P/githouse/verilator_learn/verilatoe_guide/add_sub/alu.sv
/****** alu.sv ******/
typedef enum logic [1:0] {
     add     = 2'h1,
     sub     = 2'h2,
     nop     = 2'h0
} operation_t /*verilator public*/;

module alu #(
        parameter WIDTH = 6
) (
        input clk,
        input rst,

        input  operation_t  op_in,
        input  [WIDTH-1:0]  a_in,
        input  [WIDTH-1:0]  b_in,
        input               in_valid,

        output logic [WIDTH-1:0]  out,
        output logic              out_valid
);

        operation_t  op_in_r;
        logic  [WIDTH-1:0]  a_in_r;
        logic  [WIDTH-1:0]  b_in_r;
        logic               in_valid_r;
        logic  [WIDTH-1:0]  result;

        // Register all inputs
        always_ff @ (posedge clk, posedge rst) begin
                if (rst) begin
											  op_in_r     <= nop;
                        a_in_r      <= '0;
                        b_in_r      <= '0;
                        in_valid_r  <= '0;
                end else begin
                        op_in_r    <= op_in;
                        a_in_r     <= a_in;
                        b_in_r     <= b_in;
                        in_valid_r <= in_valid;
                end
        end

        // Compute the result
        always_comb begin
                result = '0;
                if (in_valid_r) begin
                        case (op_in_r)
                                add: result = a_in_r + b_in_r;
                                sub: result = a_in_r + (~b_in_r+1'b1);
															//  sub: result = a_in_r + (~b_in_r+6'h3);

                                default: result = '0;
                        endcase
                end
        end

        // Register outputs
        always_ff @ (posedge clk, posedge rst) begin
                if (rst) begin
                        out       <= '0;
                        out_valid <= '0;
                end else begin
                        out       <= result;
                        out_valid <= in_valid_r;
									//			out_valid <= 1'b1;
                end
        end

endmodule;

P/githouse/verilator_learn/verilatoe_guide/add_sub/waveform.vcd
$version Generated by VerilatedVcd $end
$timescale 1ps $end

 $scope module TOP $end
  $var wire  6 + a_in [5:0] $end
  $var wire  6 , b_in [5:0] $end
  $var wire  1 ( clk $end
  $var wire  1 - in_valid $end
  $var wire  2 * op_in [1:0] $end
  $var wire  6 . out [5:0] $end
  $var wire  1 / out_valid $end
  $var wire  1 ) rst $end
  $scope module alu $end
   $var wire 32 0 WIDTH [31:0] $end
   $var wire  6 + a_in [5:0] $end
   $var wire  6 $ a_in_r [5:0] $end
   $var wire  6 , b_in [5:0] $end
   $var wire  6 % b_in_r [5:0] $end
   $var wire  1 ( clk $end
   $var wire  1 - in_valid $end
   $var wire  1 & in_valid_r $end
   $var wire  2 * op_in [1:0] $end
   $var wire  2 # op_in_r [1:0] $end
   $var wire  6 . out [5:0] $end
   $var wire  1 / out_valid $end
   $var wire  6 ' result [5:0] $end
   $var wire  1 ) rst $end
  $upscope $end
 $upscope $end
$enddefinitions $end


#0
b11 #
b010011 $
b100001 %
1&
b000000 '
1(
0)
b10 *
b100100 +
b111000 ,
0-
b110110 .
0/
b00000000000000000000000000000110 0
#1
0(
#2
b10 #
b100100 $
b111000 %
0&
1(
b000000 .
1/
#3
b00 #
b000000 $
b000000 %
0(
1)
b00 *
b000000 +
b000000 ,
0/
#4
1(
#5
0(
#6
1(
0)
#7
0(
#8
1(
b10 *
b010000 +
b000011 ,
1-
#9
0(
#10
b10 #
b010000 $
b000011 %
1&
b001101 '
1(
0-
#11
0(
#12
0&
b000000 '
1(
b001101 .
1/
#13
0(
#14
1(
b000000 .
0/
#15
0(
#16
1(
#17
0(
#18
1(
#19
0(
#20
1(
#21
0(
#22
1(
#23
0(
#24
1(
#25
0(
#26
1(
#27
0(
#28
1(
#29
0(
#30
1(
#31
0(
#32
1(
#33
0(
#34
1(
b01 *
b010001 +
b000010 ,
1-
#35
0(
#36
b01 #
b010001 $
b000010 %
1&
b010011 '
1(
0-
#37
0(
#38
0&
b000000 '
1(
b010011 .
1/
#39
0(
#40
1(
b000000 .
0/
#41
0(
#42
1(
#43
0(
#44
1(
b001110 +
1-
#45
0(
#46
b001110 $
1&
b010000 '
1(
0-
#47
0(
#48
0&
b000000 '
1(
b010000 .
1/
#49
0(
#50
1(
b000000 .
0/
#51
0(
#52
1(
b010011 +
b000100 ,
1-
#53
0(
#54
b010011 $
b000100 %
1&
b010111 '
1(
b10 *
b010100 +
b000101 ,
#55
0(
#56
b10 #
b010100 $
b000101 %
b001111 '
1(
0-
b010111 .
1/
#57
0(
#58
0&
b000000 '
1(
b001111 .
#59
0(
#60
1(
b000000 .
0/
#61
0(
#62
1(
#63
0(
#64
1(
#65
0(
#66
1(
#67
0(
#68
1(
b010001 +
b000011 ,
1-
#69
0(
#70
b010001 $
b000011 %
1&
b001110 '
1(
0-
#71
0(
#72
0&
b000000 '
1(
b001110 .
1/
#73
0(
#74
1(
b000000 .
0/
#75
0(
#76
1(
b001111 +
1-
#77
0(
#78
b001111 $
1&
b001100 '
1(
b01 *
b010010 +
b000100 ,
#79
0(
#80
b01 #
b010010 $
b000100 %
b010110 '
1(
0-
b001100 .
1/
#81
0(
#82
0&
b000000 '
1(
b010110 .
#83
0(
#84
1(
b000000 .
0/
#85
0(
#86
1(
#87
0(
#88
1(
#89
0(
#90
1(
#91
0(
#92
1(
#93
0(
#94
1(
#95
0(
#96
1(
#97
0(
#98
1(
#99
0(
#100
1(
#101
0(
#102
1(
#103
0(
#104
1(
#105
0(
#106
1(
#107
0(
#108
1(
#109
0(
#110
1(
b001010 +
b000001 ,
1-
#111
0(
#112
b001010 $
b000001 %
1&
b001011 '
1(
0-
#113
0(
#114
0&
b000000 '
1(
b001011 .
1/
#115
0(
#116
1(
b000000 .
0/
#117
0(
#118
1(
#119
0(
#120
1(
#121
0(
#122
1(
#123
0(
#124
1(
#125
0(
#126
1(
#127
0(
#128
1(
b10 *
b010000 +
b000100 ,
1-
#129
0(
#130
b10 #
b010000 $
b000100 %
1&
b001100 '
1(
0-
#131
0(
#132
0&
b000000 '
1(
b001100 .
1/
#133
0(
#134
1(
b01 *
b001010 +
b000001 ,
1-
b000000 .
0/
#135
0(
#136
b01 #
b001010 $
b000001 %
1&
b001011 '
1(
0-
#137
0(
#138
0&
b000000 '
1(
b001011 .
1/
#139
0(
#140
1(
b000000 .
0/
#141
0(
#142
1(
#143
0(
#144
1(
b10 *
b000000 ,
1-
#145
0(
#146
b10 #
b000000 %
1&
b001010 '
1(
0-
#147
0(
#148
0&
b000000 '
1(
b001110 +
b000100 ,
1-
b001010 .
1/
#149
0(
#150
b001110 $
b000100 %
1&
b001010 '
1(
0-
b000000 .
0/
#151
0(
#152
0&
b000000 '
1(
b001010 .
1/
#153
0(
#154
1(
b000000 .
0/
#155
0(
#156
1(
#157
0(
#158
1(
#159
0(
#160
1(
#161
0(
#162
1(
#163
0(
#164
1(
#165
0(
#166
1(
#167
0(
#168
1(
b01 *
b010100 +
b000010 ,
1-
#169
0(
#170
b01 #
b010100 $
b000010 %
1&
b010110 '
1(
0-
#171
0(
#172
0&
b000000 '
1(
b010110 .
1/
#173
0(
#174
1(
b000000 .
0/
#175
0(
#176
1(
#177
0(
#178
1(
#179
0(
#180
1(
#181
0(
#182
1(
#183
0(
#184
1(
#185
0(
#186
1(
#187
0(
#188
1(
b10 *
1-
#189
0(
#190
b10 #
1&
b010010 '
1(
b001111 +
b000100 ,
#191
0(
#192
b001111 $
b000100 %
b001011 '
1(
0-
b010010 .
1/
#193
0(
#194
0&
b000000 '
1(
b001011 .
#195
0(
#196
1(
b000000 .
0/
#197
0(
#198
1(
#199
0(
#200
1(
b01 *
b010010 +
b000010 ,
1-
#201
0(
#202
b01 #
b010010 $
b000010 %
1&
b010100 '
1(
0-
#203
0(
#204
0&
b000000 '
1(
b010100 .
1/
#205
0(
#206
1(
b000000 .
0/
#207
0(
#208
1(
#209
0(
#210
1(
b010001 +
1-
#211
0(
#212
b010001 $
1&
b010011 '
1(
0-
#213
0(
#214
0&
b000000 '
1(
b010011 .
1/
#215
0(
#216
1(
b000000 .
0/
#217
0(
#218
1(
#219
0(
#220
1(
#221
0(
#222
1(
#223
0(
#224
1(
#225
0(
#226
1(
#227
0(
#228
1(
#229
0(
#230
1(
#231
0(
#232
1(
#233
0(
#234
1(
#235
0(
#236
1(
b010100 +
b000101 ,
1-
#237
0(
#238
b010100 $
b000101 %
1&
b011001 '
1(
0-
#239
0(
#240
0&
b000000 '
1(
b011001 .
1/
#241
0(
#242
1(
b000000 .
0/
#243
0(
#244
1(
b010000 +
b000011 ,
1-
#245
0(
#246
b010000 $
b000011 %
1&
b010011 '
1(
0-
#247
0(
#248
0&
b000000 '
1(
b010011 .
1/
#249
0(
#250
1(
b000000 .
0/
#251
0(
#252
1(
#253
0(
#254
1(
#255
0(
#256
1(
#257
0(
#258
1(
#259
0(
#260
1(
#261
0(
#262
1(
#263
0(
#264
1(
#265
0(
#266
1(
#267
0(
#268
1(
#269
0(
#270
1(
#271
0(
#272
1(
#273
0(
#274
1(
#275
0(
#276
1(
#277
0(
#278
1(
#279
0(
#280
1(
#281
0(
#282
1(
#283
0(
#284
1(
#285
0(
#286
1(
#287
0(
#288
1(
b10 *
b001100 +
1-
#289
0(
#290
b10 #
b001100 $
1&
b001001 '
1(
0-
#291
0(
#292
0&
b000000 '
1(
b001001 .
1/
#293
0(
#294
1(
b01 *
b010010 +
b000101 ,
1-
b000000 .
0/
#295
0(
#296
b01 #
b010010 $
b000101 %
1&
b010111 '
1(
0-
#297
0(
#298
0&
b000000 '
1(
b010111 .
1/
